libs/__init__.py
libs/content.py
libs/renderer.py
ulanji/__init__.py
ulanji/__main__.py
ulanji/main.py
ulanji/main_window.py
ulanji/assets/renderer.html
ulanji/assets/css/bootstrap.min.css
ulanji/assets/js/renderer.js
ulanji/gui/__init__.py
ulanji/gui/main_window.py
ulanji/gui/main_window.ui
ulanji/libs/__init__.py
ulanji/libs/content.py
ulanji/libs/renderer.py
ulanji-0.0.6.dist-info/LICENSE
ulanji-0.0.6.dist-info/METADATA
ulanji-0.0.6.dist-info/WHEEL
ulanji-0.0.6.dist-info/top_level.txt
ulanji-0.0.6.dist-info/RECORD
