Metadata-Version: 2.1
Name: ulanji
Version: 0.0.6
Summary: Distraction free markdown editor
Home-page: https://github.com/jervenclark/ulanji
Author: Jerven Clark Chua
Author-email: jervenclark@gmail.com
License: UNKNOWN
Platform: UNKNOWN
Classifier: Programming Language :: Python :: 3
Classifier: License :: OSI Approved :: GNU General Public License v3 (GPLv3)
Classifier: Operating System :: OS Independent
Requires-Python: >=3.6
Requires-Dist: markdown2 (==2.3.9)
Requires-Dist: PyQt5 (==5.15.0)
Requires-Dist: PyQtWebEngine (==5.15.0)
Requires-Dist: QDarkStyle (==2.8.1)
